{
  "success": true,
  "config": {
    "start_date": "2026-01-15",
    "end_date": "2026-02-13",
    "initial_capital": 100000,
    "commission_rate": 0.0003,
    "position_size": 0.3,
    "stop_loss": -0.08,
    "take_profit": 0.25
  },
  "summary": {
    "initial_capital": 100000,
    "final_equity": 1398.1522040000013,
    "total_return_pct": -98.601847796,
    "max_drawdown_pct": -98.81700438403325,
    "total_trades": 26,
    "win_count": 0,
    "lose_count": 26,
    "win_rate": 0.0,
    "avg_profit": 0,
    "avg_loss": -246.86392730769234,
    "stop_loss_count": 26,
    "take_profit_count": 0,
    "avg_holding_days": 17.03846153846154
  },
  "trades": [
    {
      "code": "002208.SZ",
      "buy_date": "2026-01-16",
      "sell_date": "2026-02-15",
      "buy_price": 13.77,
      "sell_price": 12.41,
      "shares": 747,
      "profit": -1018.7010809999996,
      "profit_pct": -9.876543209876539,
      "reason": "STOP_LOSS",
      "strategy": "early_momentum",
      "holding_days": 30
    },
    {
      "code": "000400.SZ",
      "buy_date": "2026-01-19",
      "sell_date": "2026-02-15",
      "buy_price": 31.48,
      "sell_price": 28.09,
      "shares": 155,
      "profit": -526.7561850000001,
      "profit_pct": -10.768742058449812,
      "reason": "STOP_LOSS",
      "strategy": "early_momentum",
      "holding_days": 27
    },
    {
      "code": "000636.SZ",
      "buy_date": "2026-01-19",
      "sell_date": "2026-02-15",
      "buy_price": 20.1,
      "sell_price": 17.54,
      "shares": 347,
      "profit": -890.1459140000009,
      "profit_pct": -12.736318407960209,
      "reason": "STOP_LOSS",
      "strategy": "early_momentum",
      "holding_days": 27
    },
    {
      "code": "301285.SZ",
      "buy_date": "2026-01-20",
      "sell_date": "2026-02-15",
      "buy_price": 74.93,
      "sell_price": 66.79,
      "shares": 73,
      "profit": -595.6827010000001,
      "profit_pct": -10.863472574402776,
      "reason": "STOP_LOSS",
      "strategy": "early_momentum",
      "holding_days": 26
    },
    {
      "code": "000636.SZ",
      "buy_date": "2026-01-20",
      "sell_date": "2026-02-15",
      "buy_price": 20.71,
      "sell_price": 17.54,
      "shares": 187,
      "profit": -593.7739940000004,
      "profit_pct": -15.30661516175761,
      "reason": "STOP_LOSS",
      "strategy": "early_momentum",
      "holding_days": 26
    },
    {
      "code": "000400.SZ",
      "buy_date": "2026-01-20",
      "sell_date": "2026-02-15",
      "buy_price": 32.77,
      "sell_price": 28.09,
      "shares": 83,
      "profit": -389.13944100000026,
      "profit_pct": -14.281354897772362,
      "reason": "STOP_LOSS",
      "strategy": "early_momentum",
      "holding_days": 26
    },
    {
      "code": "002208.SZ",
      "buy_date": "2026-01-20",
      "sell_date": "2026-02-15",
      "buy_price": 14.8,
      "sell_price": 12.41,
      "shares": 90,
      "profit": -215.43507000000005,
      "profit_pct": -16.148648648648653,
      "reason": "STOP_LOSS",
      "strategy": "early_momentum",
      "holding_days": 26
    },
    {
      "code": "002208.SZ",
      "buy_date": "2026-01-21",
      "sell_date": "2026-02-15",
      "buy_price": 15.35,
      "sell_price": 12.41,
      "shares": 288,
      "profit": -847.7922239999998,
      "profit_pct": -19.153094462540714,
      "reason": "STOP_LOSS",
      "strategy": "early_momentum",
      "holding_days": 25
    },
    {
      "code": "000400.SZ",
      "buy_date": "2026-01-22",
      "sell_date": "2026-02-15",
      "buy_price": 32.41,
      "sell_price": 28.09,
      "shares": 63,
      "profit": -272.69090099999977,
      "profit_pct": -13.329219376735566,
      "reason": "STOP_LOSS",
      "strategy": "early_momentum",
      "holding_days": 24
    },
    {
      "code": "000636.SZ",
      "buy_date": "2026-01-23",
      "sell_date": "2026-02-15",
      "buy_price": 21.13,
      "sell_price": 17.54,
      "shares": 64,
      "profit": -230.096768,
      "profit_pct": -16.99006152389967,
      "reason": "STOP_LOSS",
      "strategy": "early_momentum",
      "holding_days": 23
    },
    {
      "code": "000400.SZ",
      "buy_date": "2026-01-26",
      "sell_date": "2026-02-15",
      "buy_price": 31.85,
      "sell_price": 28.09,
      "shares": 31,
      "profit": -116.82123700000004,
      "profit_pct": -11.805337519623238,
      "reason": "STOP_LOSS",
      "strategy": "early_momentum",
      "holding_days": 20
    },
    {
      "code": "002208.SZ",
      "buy_date": "2026-01-28",
      "sell_date": "2026-02-15",
      "buy_price": 14.98,
      "sell_price": 12.41,
      "shares": 52,
      "profit": -133.83359600000003,
      "profit_pct": -17.156208277703605,
      "reason": "STOP_LOSS",
      "strategy": "early_momentum",
      "holding_days": 18
    },
    {
      "code": "000636.SZ",
      "buy_date": "2026-01-29",
      "sell_date": "2026-02-15",
      "buy_price": 21.75,
      "sell_price": 17.54,
      "shares": 34,
      "profit": -143.31890800000005,
      "profit_pct": -19.356321839080465,
      "reason": "STOP_LOSS",
      "strategy": "early_momentum",
      "holding_days": 17
    },
    {
      "code": "002506.SZ",
      "buy_date": "2026-01-30",
      "sell_date": "2026-02-15",
      "buy_price": 3.6,
      "sell_price": 2.94,
      "shares": 193,
      "profit": -127.55022600000002,
      "profit_pct": -18.33333333333334,
      "reason": "STOP_LOSS",
      "strategy": "early_momentum",
      "holding_days": 16
    },
    {
      "code": "301285.SZ",
      "buy_date": "2026-01-30",
      "sell_date": "2026-02-15",
      "buy_price": 74.36,
      "sell_price": 66.79,
      "shares": 6,
      "profit": -45.54022199999996,
      "profit_pct": -10.180204410973632,
      "reason": "STOP_LOSS",
      "strategy": "early_momentum",
      "holding_days": 16
    },
    {
      "code": "002506.SZ",
      "buy_date": "2026-02-02",
      "sell_date": "2026-02-15",
      "buy_price": 3.43,
      "sell_price": 2.94,
      "shares": 132,
      "profit": -64.79642400000003,
      "profit_pct": -14.28571428571429,
      "reason": "STOP_LOSS",
      "strategy": "early_momentum",
      "holding_days": 13
    },
    {
      "code": "002208.SZ",
      "buy_date": "2026-02-02",
      "sell_date": "2026-02-15",
      "buy_price": 13.63,
      "sell_price": 12.41,
      "shares": 8,
      "profit": -9.789784000000004,
      "profit_pct": -8.950843727072638,
      "reason": "STOP_LOSS",
      "strategy": "early_momentum",
      "holding_days": 13
    },
    {
      "code": "002506.SZ",
      "buy_date": "2026-02-03",
      "sell_date": "2026-02-15",
      "buy_price": 3.42,
      "sell_price": 2.94,
      "shares": 66,
      "profit": -31.738212,
      "profit_pct": -14.035087719298245,
      "reason": "STOP_LOSS",
      "strategy": "early_momentum",
      "holding_days": 12
    },
    {
      "code": "002506.SZ",
      "buy_date": "2026-02-04",
      "sell_date": "2026-02-15",
      "buy_price": 3.49,
      "sell_price": 2.94,
      "shares": 44,
      "profit": -24.23880800000001,
      "profit_pct": -15.759312320916912,
      "reason": "STOP_LOSS",
      "strategy": "early_momentum",
      "holding_days": 11
    },
    {
      "code": "000636.SZ",
      "buy_date": "2026-02-04",
      "sell_date": "2026-02-15",
      "buy_price": 20.17,
      "sell_price": 17.54,
      "shares": 5,
      "profit": -13.176310000000013,
      "profit_pct": -13.039167079821528,
      "reason": "STOP_LOSS",
      "strategy": "early_momentum",
      "holding_days": 11
    },
    {
      "code": "002506.SZ",
      "buy_date": "2026-02-05",
      "sell_date": "2026-02-15",
      "buy_price": 4.1,
      "sell_price": 2.94,
      "shares": 29,
      "profit": -33.665578,
      "profit_pct": -28.292682926829265,
      "reason": "STOP_LOSS",
      "strategy": "early_momentum",
      "holding_days": 10
    },
    {
      "code": "000636.SZ",
      "buy_date": "2026-02-05",
      "sell_date": "2026-02-15",
      "buy_price": 21.31,
      "sell_price": 17.54,
      "shares": 4,
      "profit": -15.101047999999999,
      "profit_pct": -17.69122477709995,
      "reason": "STOP_LOSS",
      "strategy": "early_momentum",
      "holding_days": 10
    },
    {
      "code": "000636.SZ",
      "buy_date": "2026-02-10",
      "sell_date": "2026-02-15",
      "buy_price": 21.74,
      "sell_price": 17.54,
      "shares": 3,
      "profit": -12.615785999999998,
      "profit_pct": -19.319227230910762,
      "reason": "STOP_LOSS",
      "strategy": "early_momentum",
      "holding_days": 5
    },
    {
      "code": "002506.SZ",
      "buy_date": "2026-02-11",
      "sell_date": "2026-02-15",
      "buy_price": 5.47,
      "sell_price": 2.94,
      "shares": 13,
      "profit": -32.901466,
      "profit_pct": -46.25228519195612,
      "reason": "STOP_LOSS",
      "strategy": "early_momentum",
      "holding_days": 4
    },
    {
      "code": "000636.SZ",
      "buy_date": "2026-02-11",
      "sell_date": "2026-02-15",
      "buy_price": 21.79,
      "sell_price": 17.54,
      "shares": 2,
      "profit": -8.510524,
      "profit_pct": -19.50435979807251,
      "reason": "STOP_LOSS",
      "strategy": "early_momentum",
      "holding_days": 4
    },
    {
      "code": "002506.SZ",
      "buy_date": "2026-02-12",
      "sell_date": "2026-02-15",
      "buy_price": 5.18,
      "sell_price": 2.94,
      "shares": 11,
      "profit": -24.649701999999998,
      "profit_pct": -43.24324324324324,
      "reason": "STOP_LOSS",
      "strategy": "early_momentum",
      "holding_days": 3
    }
  ],
  "equity_curve": [
    {
      "date": "2026-01-15",
      "equity": 118187.437479
    },
    {
      "date": "2026-01-16",
      "equity": 101316.28162200001
    },
    {
      "date": "2026-01-17",
      "equity": 98960.45054100001
    },
    {
      "date": "2026-01-18",
      "equity": 98960.45054100001
    },
    {
      "date": "2026-01-19",
      "equity": 76581.101455
    },
    {
      "date": "2026-01-20",
      "equity": 71680.37683299999
    },
    {
      "date": "2026-01-21",
      "equity": 69618.899387
    },
    {
      "date": "2026-01-22",
      "equity": 17176.521505
    },
    {
      "date": "2026-01-23",
      "equity": 13325.179763000002
    },
    {
      "date": "2026-01-24",
      "equity": 13086.122995000002
    },
    {
      "date": "2026-01-25",
      "equity": 13086.122995000002
    },
    {
      "date": "2026-01-26",
      "equity": 12985.267179
    },
    {
      "date": "2026-01-27",
      "equity": 12920.835942000002
    },
    {
      "date": "2026-01-28",
      "equity": 12950.762254000003
    },
    {
      "date": "2026-01-29",
      "equity": 12770.226808000001
    },
    {
      "date": "2026-01-30",
      "equity": 10124.315612
    },
    {
      "date": "2026-01-31",
      "equity": 9780.355164
    },
    {
      "date": "2026-02-01",
      "equity": 9780.355164
    },
    {
      "date": "2026-02-02",
      "equity": 2970.249115000001
    },
    {
      "date": "2026-02-03",
      "equity": 2822.735191000001
    },
    {
      "date": "2026-02-04",
      "equity": 1939.846677000001
    },
    {
      "date": "2026-02-05",
      "equity": 1866.7203170000012
    },
    {
      "date": "2026-02-06",
      "equity": 1812.0236910000012
    },
    {
      "date": "2026-02-07",
      "equity": 1812.0236910000012
    },
    {
      "date": "2026-02-08",
      "equity": 1812.0236910000012
    },
    {
      "date": "2026-02-09",
      "equity": 1586.202971000001
    },
    {
      "date": "2026-02-10",
      "equity": 1584.7734050000013
    },
    {
      "date": "2026-02-11",
      "equity": 1557.413212000001
    },
    {
      "date": "2026-02-12",
      "equity": 1522.5341280000014
    },
    {
      "date": "2026-02-13",
      "equity": 1398.1522040000013
    }
  ]
}