{
  "_comment": "系统唯一参数配置 - V20.5 纯血游资起爆哲学：资金为王、顺势而为",
  "version": "2.5",
  "last_updated": "2026-03-03",
  
  "stock_filter": {
    "_description": "【全局股票漏斗铁律】实盘/复盘/回测/下载 全局共用，宁缺毋滥！",
    "min_avg_amount": 50000000.0,
    "min_avg_turnover_pct": 5.0,
    "min_intraday_turnover_pct": 5.0,
    "min_volume_multiplier": 3.0,
    "min_price": 3.0,
    "max_price": 300.0,
    "notes": "5000万均额保底 + 5%均换手粗筛 + 5%盘中换手快筛 + 3.0倍量比起爆"
  },

  "system_and_risk": {
    "_description": "取代原 config.json 的全局系统与风控参数",
    "qmt_port": 58610,
    "max_positions": 3,
    "max_single_position_value": 20000.0,
    "cutoff_time": "09:35:00",
    "order_timeout_seconds": 5,
    "max_daily_loss_pct": 0.05,
    "circuit_breaker_missing_data_rate": 0.20
  },

  "live_sniper": {
    "_description": "Tick级动能打分引擎微调参数 - V20.5纯动态Ratio版",
    "turnover_rate_per_min_min": 0.2,
    "turnover_rate_max": 300.0,
    "min_active_turnover_rate": 5.0,
    "time_decay_ratios": {
      "early_morning_rush": 1.2,
      "morning_confirm": 1.0,
      "noon_trash": 0.8,
      "tail_trap": 0.2
    },
    "scoring_bonuses": {
      "extreme_volume_ratio": 3.0,
      "extreme_vol_bonus": 10,
      "high_efficiency_turnover_min": 0.5,
      "high_turnover_bonus": 5
    }
  },

  "portfolio": {
    "_description": "Portfolio层风控参数",
    "dominance_ratio_threshold": 1.5,
    "max_drawdown_pct": 0.03,
    "min_advantage_score": 0.7
  }
}
